dev_sup
