Metadata-Version: 1.2
Name: dev-sup
Version: 0.1.2
Summary: A Django app supporting app developer.
Home-page: https://github.com/JanekKar/django-dev-sup
Author: Jan Karaszewski
Author-email: jakarwski19@gmail.com
License: BSD-3-Clause
Project-URL: Authors Github, https://github.com/JanekKar
Platform: UNKNOWN
Classifier: Environment :: Web Environment
Classifier: Framework :: Django
Classifier: Framework :: Django :: 3.2
Classifier: Intended Audience :: Developers
Classifier: License :: OSI Approved :: BSD License
Classifier: Operating System :: OS Independent
Classifier: Programming Language :: Python
Classifier: Programming Language :: Python :: 3
Classifier: Programming Language :: Python :: 3 :: Only
Classifier: Programming Language :: Python :: 3.6
Classifier: Programming Language :: Python :: 3.7
Classifier: Programming Language :: Python :: 3.8
Classifier: Topic :: Internet :: WWW/HTTP
Classifier: Topic :: Internet :: WWW/HTTP :: Dynamic Content
Requires-Python: >=3.6
